skuf/__init__.py
skuf/core.py
skuf/settings.py
skuf-0.2.1.dist-info/LICENSE
skuf-0.2.1.dist-info/METADATA
skuf-0.2.1.dist-info/WHEEL
skuf-0.2.1.dist-info/RECORD
