Metadata-Version: 2.3
Name: skuf
Version: 0.2.1
Summary: Minimal Dependency Injection & Configuration Framework for Python
License: MIT
Keywords: di,dependency-injection,container,python,env
Author: MentorSisek
Author-email: n3m0_22@mail.ru
Requires-Python: >=3.7
Classifier: License :: OSI Approved :: MIT License
Classifier: Programming Language :: Python :: 3
Classifier: Programming Language :: Python :: 3.7
Classifier: Programming Language :: Python :: 3.8
Classifier: Programming Language :: Python :: 3.9
Classifier: Programming Language :: Python :: 3.10
Classifier: Programming Language :: Python :: 3.11
Classifier: Programming Language :: Python :: 3.12
Classifier: Programming Language :: Python :: 3.13
Project-URL: Homepage, https://github.com/Tsunami43/skuf.git
